mercadopago_result/__init__.py
mercadopago_result/api_requests/__init__.py
mercadopago_result/api_requests/checkout.py
mercadopago_result/api_requests/client.py
mercadopago_result/api_requests/common.py
mercadopago_result/api_requests/document.py
mercadopago_result/authorization.py
mercadopago_result/checkout.py
mercadopago_result/client.py
mercadopago_result/common.py
mercadopago_result/constants.py
mercadopago_result/document.py
mercadopago_result/item.py
mercadopago_result/user.py
mercadopago_result-0.1.4.dist-info/LICENSE
mercadopago_result-0.1.4.dist-info/METADATA
mercadopago_result-0.1.4.dist-info/WHEEL
mercadopago_result-0.1.4.dist-info/RECORD
